FedDCM1/__init__.py
FedDCM1/client_matrix.py
FedDCM1/client_single.py
FedDCM1/dcm.py
FedDCM1/functions.py
FedDCM1/server.py
FedDCM-0.0.2.dist-info/LICENSE
FedDCM-0.0.2.dist-info/METADATA
FedDCM-0.0.2.dist-info/WHEEL
FedDCM-0.0.2.dist-info/top_level.txt
FedDCM-0.0.2.dist-info/RECORD
